LICENSE.txt
MANIFEST.in
README.rst
setup.py
createcoverage/__init__.py
createcoverage/script.py
createcoverage/tests.py
createcoverage.egg-info/PKG-INFO
createcoverage.egg-info/SOURCES.txt
createcoverage.egg-info/dependency_links.txt
createcoverage.egg-info/entry_points.txt
createcoverage.egg-info/not-zip-safe
createcoverage.egg-info/requires.txt
createcoverage.egg-info/top_level.txt