Metadata-Version: 1.0
Name: createcoverage
Version: 1.3.1
Summary: Single command to create coverage reports (assumes a bin/test)
Home-page: https://pypi.python.org/pypi/createcoverage
Author: Reinout van Rees
Author-email: reinout@vanrees.org
License: GPL
Platform: UNKNOWN
